{
  "module": "agricultural_modules.variety_trials.views",
  "imports": [
    "django_filters.rest_framework",
    "models",
    "rest_framework",
    "rest_framework.decorators",
    "rest_framework.response",
    "serializers",
    "services"
  ],
  "classes": [
    {
      "name": "TrialLocationViewSet",
      "methods": [],
      "variables": [
        "queryset",
        "serializer_class",
        "permission_classes",
        "filter_backends",
        "filterset_fields",
        "search_fields",
        "ordering_fields"
      ]
    },
    {
      "name": "TrialSeasonViewSet",
      "methods": [],
      "variables": [
        "queryset",
        "serializer_class",
        "permission_classes",
        "filter_backends",
        "filterset_fields",
        "search_fields",
        "ordering_fields"
      ]
    },
    {
      "name": "CompetitorVarietyViewSet",
      "methods": [],
      "variables": [
        "queryset",
        "serializer_class",
        "permission_classes",
        "filter_backends",
        "filterset_fields",
        "search_fields",
        "ordering_fields"
      ]
    },
    {
      "name": "VarietyTrialViewSet",
      "methods": [
        "get_serializer_class",
        "create",
        "update",
        "destroy",
        "add_variety",
        "remove_variety",
        "record_harvest",
        "record_fruit_characteristics",
        "record_plant_characteristics",
        "add_fertilization_program",
        "add_pesticide_program",
        "add_cost",
        "statistics",
        "compare_varieties",
        "strengths_weaknesses",
        "suggest_price",
        "generate_report"
      ],
      "variables": [
        "queryset",
        "permission_classes",
        "filter_backends",
        "filterset_fields",
        "search_fields",
        "ordering_fields"
      ]
    },
    {
      "name": "TrialVarietyViewSet",
      "methods": [],
      "variables": [
        "queryset",
        "serializer_class",
        "permission_classes",
        "filter_backends",
        "filterset_fields",
        "search_fields",
        "ordering_fields"
      ]
    },
    {
      "name": "TrialReplicateViewSet",
      "methods": [],
      "variables": [
        "queryset",
        "serializer_class",
        "permission_classes",
        "filter_backends",
        "filterset_fields",
        "ordering_fields"
      ]
    },
    {
      "name": "HarvestDataViewSet",
      "methods": [],
      "variables": [
        "queryset",
        "serializer_class",
        "permission_classes",
        "filter_backends",
        "filterset_fields",
        "search_fields",
        "ordering_fields"
      ]
    },
    {
      "name": "FruitCharacteristicViewSet",
      "methods": [],
      "variables": [
        "queryset",
        "serializer_class",
        "permission_classes",
        "filter_backends",
        "filterset_fields",
        "search_fields",
        "ordering_fields"
      ]
    },
    {
      "name": "PlantCharacteristicViewSet",
      "methods": [],
      "variables": [
        "queryset",
        "serializer_class",
        "permission_classes",
        "filter_backends",
        "filterset_fields",
        "search_fields",
        "ordering_fields"
      ]
    },
    {
      "name": "TrialFertilizationProgramViewSet",
      "methods": [],
      "variables": [
        "queryset",
        "serializer_class",
        "permission_classes",
        "filter_backends",
        "filterset_fields",
        "search_fields",
        "ordering_fields"
      ]
    },
    {
      "name": "TrialPesticideProgramViewSet",
      "methods": [],
      "variables": [
        "queryset",
        "serializer_class",
        "permission_classes",
        "filter_backends",
        "filterset_fields",
        "search_fields",
        "ordering_fields"
      ]
    },
    {
      "name": "TrialCostViewSet",
      "methods": [],
      "variables": [
        "queryset",
        "serializer_class",
        "permission_classes",
        "filter_backends",
        "filterset_fields",
        "search_fields",
        "ordering_fields"
      ]
    },
    {
      "name": "TrialReportViewSet",
      "methods": [],
      "variables": [
        "queryset",
        "serializer_class",
        "permission_classes",
        "filter_backends",
        "filterset_fields",
        "search_fields",
        "ordering_fields"
      ]
    }
  ],
  "functions": [
    {
      "name": "get_serializer_class",
      "parameters": [
        "self"
      ]
    },
    {
      "name": "create",
      "parameters": [
        "self",
        "request"
      ]
    },
    {
      "name": "update",
      "parameters": [
        "self",
        "request"
      ]
    },
    {
      "name": "destroy",
      "parameters": [
        "self",
        "request"
      ]
    },
    {
      "name": "add_variety",
      "parameters": [
        "self",
        "request",
        "pk"
      ]
    },
    {
      "name": "remove_variety",
      "parameters": [
        "self",
        "request",
        "pk"
      ]
    },
    {
      "name": "record_harvest",
      "parameters": [
        "self",
        "request",
        "pk"
      ]
    },
    {
      "name": "record_fruit_characteristics",
      "parameters": [
        "self",
        "request",
        "pk"
      ]
    },
    {
      "name": "record_plant_characteristics",
      "parameters": [
        "self",
        "request",
        "pk"
      ]
    },
    {
      "name": "add_fertilization_program",
      "parameters": [
        "self",
        "request",
        "pk"
      ]
    },
    {
      "name": "add_pesticide_program",
      "parameters": [
        "self",
        "request",
        "pk"
      ]
    },
    {
      "name": "add_cost",
      "parameters": [
        "self",
        "request",
        "pk"
      ]
    },
    {
      "name": "statistics",
      "parameters": [
        "self",
        "request",
        "pk"
      ]
    },
    {
      "name": "compare_varieties",
      "parameters": [
        "self",
        "request",
        "pk"
      ]
    },
    {
      "name": "strengths_weaknesses",
      "parameters": [
        "self",
        "request",
        "pk"
      ]
    },
    {
      "name": "suggest_price",
      "parameters": [
        "self",
        "request",
        "pk"
      ]
    },
    {
      "name": "generate_report",
      "parameters": [
        "self",
        "request",
        "pk"
      ]
    }
  ],
  "variables": []
}