{
  "$schema": "https://json-schema.org/draft-07/schema#",
  "name": "Store ERP Design Tokens",
  "version": "1.0.0",
  "description": "Design tokens extracted from Gaara Seeds brand (gaaraseeds.com)",
  "lastUpdated": "2025-11-07",
  
  "colors": {
    "primary": {
      "name": "Gaara Green",
      "description": "Main brand color representing agricultural growth and nature",
      "50": "#f0fdf4",
      "100": "#dcfce7",
      "200": "#bbf7d0",
      "300": "#86efac",
      "400": "#4ade80",
      "500": "#22c55e",
      "600": "#16a34a",
      "700": "#15803d",
      "800": "#166534",
      "900": "#14532d",
      "main": "#22c55e"
    },
    
    "secondary": {
      "name": "Earth Brown",
      "description": "Secondary color representing earth, seeds, and soil",
      "50": "#fdf8f6",
      "100": "#f2e8e5",
      "200": "#eaddd7",
      "300": "#e0cec7",
      "400": "#d2bab0",
      "500": "#bfa094",
      "600": "#a18072",
      "700": "#977669",
      "800": "#846358",
      "900": "#43302b",
      "main": "#bfa094"
    },
    
    "accent": {
      "name": "Agricultural Gold",
      "description": "Accent color representing harvest, success, and premium quality",
      "50": "#fffbeb",
      "100": "#fef3c7",
      "200": "#fde68a",
      "300": "#fcd34d",
      "400": "#fbbf24",
      "500": "#f59e0b",
      "600": "#d97706",
      "700": "#b45309",
      "800": "#92400e",
      "900": "#78350f",
      "main": "#f59e0b"
    },
    
    "success": {
      "name": "Success Green",
      "description": "Success state color",
      "50": "#ecfdf5",
      "100": "#d1fae5",
      "200": "#a7f3d0",
      "300": "#6ee7b7",
      "400": "#34d399",
      "500": "#10b981",
      "600": "#059669",
      "700": "#047857",
      "800": "#065f46",
      "900": "#064e3b",
      "main": "#10b981"
    },
    
    "warning": {
      "name": "Warning Orange",
      "description": "Warning state color",
      "50": "#fffbeb",
      "100": "#fef3c7",
      "200": "#fde68a",
      "300": "#fcd34d",
      "400": "#fbbf24",
      "500": "#f59e0b",
      "600": "#d97706",
      "700": "#b45309",
      "800": "#92400e",
      "900": "#78350f",
      "main": "#f59e0b"
    },
    
    "danger": {
      "name": "Danger Red",
      "description": "Error/danger state color",
      "50": "#fef2f2",
      "100": "#fee2e2",
      "200": "#fecaca",
      "300": "#fca5a5",
      "400": "#f87171",
      "500": "#ef4444",
      "600": "#dc2626",
      "700": "#b91c1c",
      "800": "#991b1b",
      "900": "#7f1d1d",
      "main": "#ef4444"
    },
    
    "info": {
      "name": "Info Blue",
      "description": "Information state color",
      "50": "#eff6ff",
      "100": "#dbeafe",
      "200": "#bfdbfe",
      "300": "#93c5fd",
      "400": "#60a5fa",
      "500": "#3b82f6",
      "600": "#2563eb",
      "700": "#1d4ed8",
      "800": "#1e40af",
      "900": "#1e3a8a",
      "main": "#3b82f6"
    },
    
    "neutral": {
      "name": "Gray Scale",
      "description": "Neutral colors for text, borders, and backgrounds",
      "50": "#fafafa",
      "100": "#f4f4f5",
      "200": "#e4e4e7",
      "300": "#d4d4d8",
      "400": "#a1a1aa",
      "500": "#71717a",
      "600": "#52525b",
      "700": "#3f3f46",
      "800": "#27272a",
      "900": "#18181b"
    },
    
    "background": {
      "primary": "#ffffff",
      "secondary": "#f8fafc",
      "tertiary": "#f1f5f9",
      "dark": "#0f172a"
    },
    
    "text": {
      "primary": "#1e293b",
      "secondary": "#64748b",
      "tertiary": "#94a3b8",
      "inverse": "#ffffff",
      "disabled": "#cbd5e1"
    },
    
    "border": {
      "light": "#f1f5f9",
      "base": "#e2e8f0",
      "dark": "#cbd5e1",
      "focus": "#22c55e"
    }
  },
  
  "typography": {
    "fontFamily": {
      "sans": ["Cairo", "Tajawal", "system-ui", "-apple-system", "sans-serif"],
      "arabic": ["Cairo", "Tajawal"],
      "mono": ["Courier New", "Consolas", "Monaco", "monospace"]
    },
    
    "fontSize": {
      "xs": "0.75rem",
      "sm": "0.875rem",
      "base": "1rem",
      "lg": "1.125rem",
      "xl": "1.25rem",
      "2xl": "1.5rem",
      "3xl": "1.875rem",
      "4xl": "2.25rem",
      "5xl": "3rem",
      "6xl": "3.75rem"
    },
    
    "fontWeight": {
      "light": 300,
      "normal": 400,
      "medium": 500,
      "semibold": 600,
      "bold": 700,
      "extrabold": 800,
      "black": 900
    },
    
    "lineHeight": {
      "none": 1,
      "tight": 1.25,
      "snug": 1.375,
      "normal": 1.5,
      "relaxed": 1.625,
      "loose": 2
    },
    
    "letterSpacing": {
      "tighter": "-0.05em",
      "tight": "-0.025em",
      "normal": "0",
      "wide": "0.025em",
      "wider": "0.05em",
      "widest": "0.1em"
    }
  },
  
  "spacing": {
    "0": "0",
    "px": "1px",
    "0.5": "0.125rem",
    "1": "0.25rem",
    "1.5": "0.375rem",
    "2": "0.5rem",
    "2.5": "0.625rem",
    "3": "0.75rem",
    "3.5": "0.875rem",
    "4": "1rem",
    "5": "1.25rem",
    "6": "1.5rem",
    "7": "1.75rem",
    "8": "2rem",
    "9": "2.25rem",
    "10": "2.5rem",
    "11": "2.75rem",
    "12": "3rem",
    "14": "3.5rem",
    "16": "4rem",
    "20": "5rem",
    "24": "6rem",
    "28": "7rem",
    "32": "8rem",
    "36": "9rem",
    "40": "10rem",
    "44": "11rem",
    "48": "12rem",
    "52": "13rem",
    "56": "14rem",
    "60": "15rem",
    "64": "16rem",
    "72": "18rem",
    "80": "20rem",
    "96": "24rem"
  },
  
  "borderRadius": {
    "none": "0",
    "sm": "0.125rem",
    "base": "0.25rem",
    "md": "0.375rem",
    "lg": "0.5rem",
    "xl": "0.75rem",
    "2xl": "1rem",
    "3xl": "1.5rem",
    "full": "9999px"
  },
  
  "shadows": {
    "none": "none",
    "sm": "0 1px 2px 0 rgba(0, 0, 0, 0.05)",
    "base": "0 1px 3px 0 rgba(0, 0, 0, 0.1), 0 1px 2px 0 rgba(0, 0, 0, 0.06)",
    "md": "0 4px 6px -1px rgba(0, 0, 0, 0.1), 0 2px 4px -1px rgba(0, 0, 0, 0.06)",
    "lg": "0 10px 15px -3px rgba(0, 0, 0, 0.1), 0 4px 6px -2px rgba(0, 0, 0, 0.05)",
    "xl": "0 20px 25px -5px rgba(0, 0, 0, 0.1), 0 10px 10px -5px rgba(0, 0, 0, 0.04)",
    "2xl": "0 25px 50px -12px rgba(0, 0, 0, 0.25)",
    "inner": "inset 0 2px 4px 0 rgba(0, 0, 0, 0.06)"
  },
  
  "transitions": {
    "none": "none",
    "fast": "150ms cubic-bezier(0.4, 0, 0.2, 1)",
    "base": "200ms cubic-bezier(0.4, 0, 0.2, 1)",
    "slow": "300ms cubic-bezier(0.4, 0, 0.2, 1)",
    "slower": "500ms cubic-bezier(0.4, 0, 0.2, 1)"
  },
  
  "zIndex": {
    "auto": "auto",
    "0": 0,
    "10": 10,
    "20": 20,
    "30": 30,
    "40": 40,
    "50": 50,
    "dropdown": 1000,
    "sticky": 1020,
    "fixed": 1030,
    "modalBackdrop": 1040,
    "modal": 1050,
    "popover": 1060,
    "tooltip": 1070
  },
  
  "breakpoints": {
    "sm": "640px",
    "md": "768px",
    "lg": "1024px",
    "xl": "1280px",
    "2xl": "1536px"
  }
}

