{
  "project": "Gaara ERP v12",
  "version": "12.0.0",
  "last_updated": "2026-01-17T12:00:00",
  "global_system_version": "35.0_singularity",
  "mode": "adoption",
  "speckit_status": {
    "constitution": "completed",
    "specify": "completed",
    "plan": "completed",
    "clarify": "completed",
    "tasks": "completed",
    "implement": "in_progress"
  },
  "implemented_files": {
    "2026-01-17": [
      "backend/src/models/tenant.py",
      "backend/src/models/tenant_sqlalchemy.py",
      "backend/src/middleware/tenant_middleware.py",
      "backend/src/middleware/flask_tenant_middleware.py",
      "backend/src/services/tenant_service.py",
      "backend/src/routes/tenant_routes.py",
      "backend/src/routes/tenant_api.py",
      "backend/src/database/seeds/tenant_plans_seed.py",
      "backend/src/database/seeds/__init__.py",
      "backend/tests/test_tenant.py",
      "backend/tests/test_tenant_api.py",
      "gaara-erp-frontend/src/services/tenantService.js",
      "gaara-erp-frontend/src/contexts/TenantContext.jsx",
      "gaara-erp-frontend/src/components/layout/TenantSelector.jsx",
      "gaara-erp-frontend/src/components/tenants/TenantUsersDialog.jsx",
      "gaara-erp-frontend/src/components/tenants/index.js",
      "gaara-erp-frontend/src/pages/core/MultiTenancyPage.jsx (updated)",
      "backend/src/main.py (updated - registered tenant_bp + middleware)",
      ".pre-commit-config.yaml",
      "errors/CRITICAL_ERRORS_REPORT.md",
      "TODO_MULTI_TENANCY_FINAL.md"
    ]
  },
  "specifications": {
    "master_spec": "specs/GAARA_ERP_MASTER.spec.md",
    "multi_tenancy_spec": "specs/multi_tenancy.spec.md",
    "hr_module_spec": "specs/hr_module.spec.md",
    "mfa_security_spec": "specs/mfa_security.spec.md"
  },
  "plans": {
    "master_plan": "plans/GAARA_ERP_MASTER.plan.md",
    "phase0_plan": "plans/phase0_critical.plan.md"
  },
  "critical_files": {
    "constitution": "CONSTITUTION.md",
    "file_registry": ".memory/file_registry.json",
    "current_context": ".memory/context/current_task.md",
    "global_tools": "global_v35.0_singularity/global/tools/"
  },
  "decisions": {
    "security": {
      "mfa_methods": ["sms", "totp", "email"],
      "jwt_access_lifetime": "1h",
      "jwt_refresh_lifetime": "24h",
      "password_policy": "strong",
      "min_password_length": 12
    },
    "multi_tenancy": {
      "isolation_strategy": "schema_based",
      "identification_methods": ["subdomain", "custom_domain", "header"]
    },
    "business": {
      "accounting_standards": ["IFRS", "GAAP"],
      "multi_currency": true,
      "base_currency": "SAR"
    },
    "ai": {
      "external_api_allowed": true,
      "fallback_behavior": "graceful_degradation",
      "cost_management": "quota_per_customer"
    },
    "deployment": {
      "targets": ["self_hosted", "cloud_saas"],
      "containerization": "docker"
    },
    "agricultural": {
      "module_scope": "core",
      "required": true
    }
  },
  "audit_results": {
    "total_modules": 123,
    "complete_80_plus": 49,
    "partial_40_79": 74,
    "empty_under_40": 0,
    "average_score": 78.7
  },
  "implementation_ready": true,
  "next_step": "/speckit.implement",
  "context": {
    "current_session": "requirements_approved",
    "phase": "ready_for_phase_1"
  }
}
